acadia/__init__.py
acadia/histogram.py
acadia/preprocessing.py
acadia/shape.py
acadia/space.py
acadia/tone.py
acadia-0.1.1.dist-info/LICENSE
acadia-0.1.1.dist-info/METADATA
acadia-0.1.1.dist-info/WHEEL
acadia-0.1.1.dist-info/top_level.txt
acadia-0.1.1.dist-info/RECORD
