Metadata-Version: 2.1
Name: acadia
Version: 0.1.1
Summary: A tool to create accessible audio diagrams
Author-email: Sergey Monakhov <monahovserg@gmail.com>
Project-URL: homepage, https://github.com/monaxov/acadia
Project-URL: repository, https://github.com/monaxov/acadia.git
Keywords: Accessibility,Accessible,Assistive,Blind,Visually impaired,Low vision,Screenreader
Classifier: Development Status :: 4 - Beta
Classifier: Programming Language :: Python :: 3
Classifier: License :: OSI Approved :: MIT License
Classifier: Operating System :: OS Independent
Classifier: Intended Audience :: Education
Classifier: Intended Audience :: Science/Research
Requires-Python: >=3.8
License-File: LICENSE
Requires-Dist: numpy
Requires-Dist: sounddevice
Requires-Dist: soundfile
